odoo/addons/web_assets_warmup/README.rst
odoo/addons/web_assets_warmup/__init__.py
odoo/addons/web_assets_warmup/__manifest__.py
odoo/addons/web_assets_warmup/hooks.py
odoo/addons/web_assets_warmup/data/ir_cron.xml
odoo/addons/web_assets_warmup/i18n/it.po
odoo/addons/web_assets_warmup/i18n/web_assets_warmup.pot
odoo/addons/web_assets_warmup/models/__init__.py
odoo/addons/web_assets_warmup/models/ir_actions_report.py
odoo/addons/web_assets_warmup/readme/CONTRIBUTORS.rst
odoo/addons/web_assets_warmup/readme/DESCRIPTION.rst
odoo/addons/web_assets_warmup/static/description/icon.png
odoo/addons/web_assets_warmup/static/description/index.html
odoo14_addon_web_assets_warmup-14.0.1.0.1.dev5.dist-info/METADATA
odoo14_addon_web_assets_warmup-14.0.1.0.1.dev5.dist-info/WHEEL
odoo14_addon_web_assets_warmup-14.0.1.0.1.dev5.dist-info/top_level.txt
odoo14_addon_web_assets_warmup-14.0.1.0.1.dev5.dist-info/RECORD
